zigzag/__init__.py
zigzag/core.cpython-312-darwin.so
zigzag/core.pyx
zigzag/plotting.py
zigzag_reload-0.3.5.dist-info/LICENSE.txt
zigzag_reload-0.3.5.dist-info/METADATA
zigzag_reload-0.3.5.dist-info/WHEEL
zigzag_reload-0.3.5.dist-info/RECORD
