Metadata-Version: 2.3
Name: zigzag-reload
Version: 0.3.5
Summary: Package for finding peaks and valleys of time series.
License: BSD-3-Clause
Author: generativist
Author-email: jbn@abreka.com
Requires-Python: >=3.10,<3.13
Classifier: License :: OSI Approved :: BSD License
Classifier: Programming Language :: Python :: 3
Classifier: Programming Language :: Python :: 3.10
Classifier: Programming Language :: Python :: 3.11
Classifier: Programming Language :: Python :: 3.12
Requires-Dist: Cython (>=0.29)
Requires-Dist: numpy (==1.26.0)
Project-URL: Homepage, https://github.com/zillionare/ZigZag
Project-URL: Repository, https://github.com/zillionare/ZigZag
